setup.py
hook/__init__.py
hook/constants.py
hook/hook.py
sceptre_deployment_hook.egg-info/PKG-INFO
sceptre_deployment_hook.egg-info/SOURCES.txt
sceptre_deployment_hook.egg-info/dependency_links.txt
sceptre_deployment_hook.egg-info/entry_points.txt
sceptre_deployment_hook.egg-info/not-zip-safe
sceptre_deployment_hook.egg-info/top_level.txt
test/__init__.py
test/test_hook.py