Metadata-Version: 2.1
Name: sceptre-deployment-hook
Version: 0.0.19
Summary: Sceptre hook to measure stack deployment time
Home-page: https://gitlab.com/verenigingcoin/open-source/sceptre-hooks/deployment-hook
Author: Vereniging COIN
Author-email: devops@coin.nl
License: Apache-2.0
Keywords: COIN,AWS,Sceptre
Platform: any
Classifier: Development Status :: 4 - Beta
Classifier: Intended Audience :: Developers
Classifier: Topic :: Software Development :: Libraries
Classifier: License :: OSI Approved :: MIT License
Classifier: Programming Language :: Python :: 3.7
Requires-Python: >=3.7
